setup.py
jupyter_pip.egg-info/PKG-INFO
jupyter_pip.egg-info/SOURCES.txt
jupyter_pip.egg-info/dependency_links.txt
jupyter_pip.egg-info/top_level.txt
jupyterpip/__init__.py