Metadata-Version: 1.1
Name: jupyter-pip
Version: 0.1
Summary: Allows IPython notebook extension authors to make their extension pip installable!
Home-page: https://github.com/jdfreder/jupyter-pip
Author: Jonathan Frederic
Author-email: jon.freder@gmail.com
License: New BSD License
Keywords: python jupyter ipython javascript nbextension deployment pip install package extension
Platform: UNKNOWN
Classifier: Development Status :: 4 - Beta
Classifier: Programming Language :: Python
Classifier: License :: OSI Approved
